ss_python_gitlab/__init__.py
ss_python_gitlab/cli.py
ss_python_gitlab/py.typed
ss_python_gitlab/settings.py
ss_python_gitlab-1.0.0.dist-info/LICENSE
ss_python_gitlab-1.0.0.dist-info/METADATA
ss_python_gitlab-1.0.0.dist-info/WHEEL
ss_python_gitlab-1.0.0.dist-info/entry_points.txt
ss_python_gitlab-1.0.0.dist-info/top_level.txt
ss_python_gitlab-1.0.0.dist-info/RECORD
