Metadata-Version: 2.1
Name: ss-python-gitlab
Version: 1.0.0
Summary: GitLab Demo of Serious Scaffold Python
Author-email: huxuan <i@huxuan.org>
License: MIT
Project-URL: documentation, https://serious-scaffold.gitlab.io/ss-python-gitlab
Project-URL: issue, https://gitlab.com/serious-scaffold/ss-python-gitlab/-/issues
Project-URL: repository, https://gitlab.com/serious-scaffold/ss-python-gitlab
Keywords: copier-template,full-development-lifecycle,project-template,serious-scaffold
Classifier: Development Status :: 3 - Alpha
Classifier: License :: OSI Approved :: MIT License
Classifier: Operating System :: OS Independent
Classifier: Programming Language :: Python :: 3 :: Only
Classifier: Programming Language :: Python :: 3.9
Classifier: Programming Language :: Python :: 3.10
Classifier: Programming Language :: Python :: 3.11
Classifier: Programming Language :: Python :: 3.12
Classifier: Programming Language :: Python :: 3.13
Requires-Python: >=3.9
License-File: LICENSE
Requires-Dist: pydantic-settings
Requires-Dist: typer[all]
